<?xml version="1.0" ?>
<Recipe name="TKX3" version="1.0">
  <MetaData>
    <CreatedAt>2026-03-16T15:15:18</CreatedAt>
    <Description/>
  </MetaData>
  <FindWaferEdge>
    <UseUniversalParams>False</UseUniversalParams>
    <WaferAlignLeftParam Name="WaferAlign Left Parm">
      <KernelSize>112</KernelSize>
      <EdgeThreshold>2696</EdgeThreshold>
      <NumRegions>30</NumRegions>
      <BorderIgnorePct>0.050</BorderIgnorePct>
      <RansacThreshold>3.0</RansacThreshold>
      <EdgePolarity>ANY</EdgePolarity>
    </WaferAlignLeftParam>
    <WaferAlignRightParam Name="WaferAlign Right Parm">
      <KernelSize>75</KernelSize>
      <EdgeThreshold>2305</EdgeThreshold>
      <NumRegions>30</NumRegions>
      <BorderIgnorePct>0.050</BorderIgnorePct>
      <RansacThreshold>3.0</RansacThreshold>
      <EdgePolarity>ANY</EdgePolarity>
    </WaferAlignRightParam>
    <WaferAlignTopParam Name="WaferAlign Top Parm">
      <KernelSize>9</KernelSize>
      <EdgeThreshold>500</EdgeThreshold>
      <NumRegions>30</NumRegions>
      <BorderIgnorePct>0.05</BorderIgnorePct>
      <RansacThreshold>3.0</RansacThreshold>
      <EdgePolarity>ANY</EdgePolarity>
    </WaferAlignTopParam>
    <WaferAlignBotParam Name="WaferAlign Bot Parm">
      <KernelSize>9</KernelSize>
      <EdgeThreshold>500</EdgeThreshold>
      <NumRegions>30</NumRegions>
      <BorderIgnorePct>0.05</BorderIgnorePct>
      <RansacThreshold>3.0</RansacThreshold>
      <EdgePolarity>ANY</EdgePolarity>
    </WaferAlignBotParam>
  </FindWaferEdge>
  <FindPattern>
    <MatchThreshold>50.0</MatchThreshold>
    <NumFeatures>128</NumFeatures>
    <GradThrPct>87.8</GradThrPct>
    <TSpread>1</TSpread>
    <HystKernel>0</HystKernel>
    <SearchMode>Simple (Fast)</SearchMode>
    <TemplatePath>C:\Users\adrain.lim\OneDrive - QES (Asia-Pacific) Sdn Bhd\Desktop\EmguFindEdge\recipes\TKX3_template.png</TemplatePath>
    <TemplateCropCX>412.0</TemplateCropCX>
    <TemplateCropCY>624.0</TemplateCropCY>
    <DetectionMaskPath/>
  </FindPattern>
</Recipe>
